excelj/__init__.py
excelj/excelj.py
excelj-0.1.dist-info/METADATA
excelj-0.1.dist-info/WHEEL
excelj-0.1.dist-info/entry_points.txt
excelj-0.1.dist-info/top_level.txt
excelj-0.1.dist-info/RECORD
